{"0":{"is_add_obstacles":false},"1":{"is_add_obstacles":true,"pos":{"0":{"x":182,"y":154},"1":{"x":212,"y":195},"2":{"x":55,"y":143},"3":{"x":112,"y":44},"4":{"x":184,"y":27}}},"2":{"is_add_obstacles":true,"pos":{"0":{"x":45,"y":70},"1":{"x":98,"y":45},"2":{"x":131,"y":11},"3":{"x":79,"y":205},"4":{"x":47,"y":145}}},"3":{"is_add_obstacles":true,"pos":{"0":{"x":36,"y":141},"1":{"x":104,"y":220},"2":{"x":130,"y":102},"3":{"x":79,"y":199},"4":{"x":95,"y":207}}},"4":{"is_add_obstacles":true,"pos":{"0":{"x":152,"y":165},"1":{"x":193,"y":158},"2":{"x":241,"y":91},"3":{"x":241,"y":85},"4":{"x":67,"y":229}}},"5":{"is_add_obstacles":true,"pos":{"0":{"x":200,"y":180},"1":{"x":158,"y":118},"2":{"x":230,"y":201},"3":{"x":203,"y":186},"4":{"x":142,"y":223}}},"6":{"is_add_obstacles":true,"pos":{"0":{"x":110,"y":108},"1":{"x":172,"y":184},"2":{"x":112,"y":34},"3":{"x":52,"y":46},"4":{"x":156,"y":111}}},"7":{"is_add_obstacles":true,"pos":{"0":{"x":181,"y":104},"1":{"x":79,"y":222},"2":{"x":127,"y":39},"3":{"x":58,"y":91},"4":{"x":186,"y":43}}},"8":{"is_add_obstacles":true,"pos":{"0":{"x":126,"y":21},"1":{"x":180,"y":156},"2":{"x":93,"y":159},"3":{"x":93,"y":205},"4":{"x":112,"y":103}}},"9":{"is_add_obstacles":true,"pos":{"0":{"x":81,"y":136},"1":{"x":247,"y":47},"2":{"x":228,"y":89},"3":{"x":184,"y":54},"4":{"x":244,"y":191}}}}