{"0":{"is_add_obstacles":false},"1":{"is_add_obstacles":true,"pos":{"0":{"x":31,"y":73},"1":{"x":212,"y":214},"2":{"x":47,"y":82},"3":{"x":20,"y":185},"4":{"x":110,"y":156}}},"2":{"is_add_obstacles":true,"pos":{"0":{"x":185,"y":31},"1":{"x":184,"y":54},"2":{"x":51,"y":69},"3":{"x":89,"y":187},"4":{"x":208,"y":198}}},"3":{"is_add_obstacles":true,"pos":{"0":{"x":188,"y":68},"1":{"x":166,"y":101},"2":{"x":73,"y":220},"3":{"x":91,"y":225},"4":{"x":52,"y":50}}},"4":{"is_add_obstacles":true,"pos":{"0":{"x":165,"y":91},"1":{"x":85,"y":156},"2":{"x":185,"y":86},"3":{"x":241,"y":66},"4":{"x":132,"y":93}}},"5":{"is_add_obstacles":true,"pos":{"0":{"x":144,"y":211},"1":{"x":148,"y":106},"2":{"x":166,"y":148},"3":{"x":88,"y":209},"4":{"x":102,"y":168}}},"6":{"is_add_obstacles":true,"pos":{"0":{"x":154,"y":22},"1":{"x":126,"y":27},"2":{"x":80,"y":39},"3":{"x":47,"y":140},"4":{"x":174,"y":185}}},"7":{"is_add_obstacles":true,"pos":{"0":{"x":166,"y":167},"1":{"x":171,"y":156},"2":{"x":218,"y":209},"3":{"x":128,"y":165},"4":{"x":81,"y":140}}},"8":{"is_add_obstacles":true,"pos":{"0":{"x":206,"y":80},"1":{"x":177,"y":128},"2":{"x":197,"y":167},"3":{"x":229,"y":70},"4":{"x":105,"y":79}}},"9":{"is_add_obstacles":true,"pos":{"0":{"x":139,"y":99},"1":{"x":237,"y":37},"2":{"x":232,"y":54},"3":{"x":236,"y":208},"4":{"x":99,"y":99}}}}