{"0":{"is_add_obstacles":false},"1":{"is_add_obstacles":true,"pos":{"0":{"x":9,"y":59},"1":{"x":86,"y":55},"2":{"x":89,"y":34},"3":{"x":81,"y":40},"4":{"x":103,"y":13}}},"2":{"is_add_obstacles":true,"pos":{"0":{"x":158,"y":25},"1":{"x":22,"y":37},"2":{"x":25,"y":11},"3":{"x":9,"y":50},"4":{"x":22,"y":41}}},"3":{"is_add_obstacles":true,"pos":{"0":{"x":3,"y":16},"1":{"x":141,"y":32},"2":{"x":152,"y":45},"3":{"x":80,"y":54},"4":{"x":14,"y":35}}},"4":{"is_add_obstacles":true,"pos":{"0":{"x":110,"y":1},"1":{"x":2,"y":34},"2":{"x":3,"y":36},"3":{"x":3,"y":54},"4":{"x":156,"y":4}}},"5":{"is_add_obstacles":true,"pos":{"0":{"x":115,"y":52},"1":{"x":102,"y":41},"2":{"x":111,"y":58},"3":{"x":66,"y":43},"4":{"x":144,"y":49}}},"6":{"is_add_obstacles":true,"pos":{"0":{"x":115,"y":46},"1":{"x":129,"y":34},"2":{"x":113,"y":4},"3":{"x":135,"y":40},"4":{"x":1,"y":52}}},"7":{"is_add_obstacles":true,"pos":{"0":{"x":142,"y":24},"1":{"x":60,"y":4},"2":{"x":40,"y":49},"3":{"x":158,"y":46},"4":{"x":130,"y":40}}},"8":{"is_add_obstacles":true,"pos":{"0":{"x":3,"y":20},"1":{"x":129,"y":40},"2":{"x":116,"y":46},"3":{"x":86,"y":40},"4":{"x":61,"y":7}}},"9":{"is_add_obstacles":true,"pos":{"0":{"x":20,"y":20},"1":{"x":2,"y":21},"2":{"x":124,"y":52},"3":{"x":55,"y":43},"4":{"x":133,"y":31}}}}