{"0":{"is_add_obstacles":false},"1":{"is_add_obstacles":true,"pos":{"0":{"x":100,"y":22},"1":{"x":103,"y":22},"2":{"x":21,"y":8},"3":{"x":151,"y":10},"4":{"x":154,"y":59}}},"2":{"is_add_obstacles":false,"pos":{"0":{"x":83,"y":59},"1":{"x":44,"y":35},"2":{"x":72,"y":24},"3":{"x":49,"y":45},"4":{"x":41,"y":44}}},"3":{"is_add_obstacles":true,"pos":{"0":{"x":63,"y":22},"1":{"x":9,"y":42},"2":{"x":150,"y":35},"3":{"x":108,"y":19},"4":{"x":81,"y":34}}},"4":{"is_add_obstacles":false,"pos":{"0":{"x":123,"y":38},"1":{"x":31,"y":27},"2":{"x":85,"y":0},"3":{"x":50,"y":27},"4":{"x":31,"y":6}}},"5":{"is_add_obstacles":true,"pos":{"0":{"x":123,"y":25},"1":{"x":11,"y":19},"2":{"x":131,"y":52},"3":{"x":118,"y":19},"4":{"x":47,"y":57}}},"6":{"is_add_obstacles":false,"pos":{"0":{"x":61,"y":0},"1":{"x":150,"y":35},"2":{"x":105,"y":26},"3":{"x":0,"y":61},"4":{"x":62,"y":50}}},"7":{"is_add_obstacles":true,"pos":{"0":{"x":108,"y":31},"1":{"x":111,"y":58},"2":{"x":50,"y":4},"3":{"x":137,"y":31},"4":{"x":156,"y":11}}},"8":{"is_add_obstacles":false,"pos":{"0":{"x":57,"y":5},"1":{"x":94,"y":15},"2":{"x":61,"y":15},"3":{"x":27,"y":6},"4":{"x":99,"y":42}}},"9":{"is_add_obstacles":true,"pos":{"0":{"x":91,"y":33},"1":{"x":73,"y":55},"2":{"x":91,"y":2},"3":{"x":140,"y":22},"4":{"x":30,"y":37}}}}