{"0":{"is_add_obstacles":false},"1":{"is_add_obstacles":true,"pos":{"0":{"x":25,"y":17},"1":{"x":27,"y":21},"2":{"x":17,"y":7},"3":{"x":6,"y":10},"4":{"x":25,"y":10}}},"2":{"is_add_obstacles":true,"pos":{"0":{"x":23,"y":17},"1":{"x":22,"y":3},"2":{"x":18,"y":2},"3":{"x":17,"y":31},"4":{"x":27,"y":24}}},"3":{"is_add_obstacles":true,"pos":{"0":{"x":23,"y":9},"1":{"x":14,"y":6},"2":{"x":7,"y":27},"3":{"x":3,"y":30},"4":{"x":7,"y":18}}},"4":{"is_add_obstacles":true},"5":{"is_add_obstacles":true},"6":{"is_add_obstacles":true},"7":{"is_add_obstacles":true},"8":{"is_add_obstacles":true},"9":{"is_add_obstacles":true}}