{"0":{"is_add_obstacles":false},"1":{"is_add_obstacles":true,"pos":{"0":{"x":130,"y":31},"1":{"x":155,"y":17},"2":{"x":61,"y":25},"3":{"x":136,"y":35},"4":{"x":37,"y":22}}},"2":{"is_add_obstacles":false,"pos":{"0":{"x":100,"y":56},"1":{"x":52,"y":48},"2":{"x":79,"y":3},"3":{"x":119,"y":50},"4":{"x":106,"y":8}}},"3":{"is_add_obstacles":true,"pos":{"0":{"x":148,"y":61},"1":{"x":36,"y":1},"2":{"x":91,"y":29},"3":{"x":134,"y":31},"4":{"x":108,"y":49}}},"4":{"is_add_obstacles":false,"pos":{"0":{"x":101,"y":41},"1":{"x":42,"y":21},"2":{"x":34,"y":15},"3":{"x":132,"y":39},"4":{"x":115,"y":5}}},"5":{"is_add_obstacles":true,"pos":{"0":{"x":81,"y":52},"1":{"x":10,"y":20},"2":{"x":72,"y":28},"3":{"x":152,"y":6},"4":{"x":69,"y":33}}},"6":{"is_add_obstacles":false,"pos":{"0":{"x":118,"y":44},"1":{"x":117,"y":48},"2":{"x":54,"y":17},"3":{"x":51,"y":0},"4":{"x":73,"y":30}}},"7":{"is_add_obstacles":true,"pos":{"0":{"x":134,"y":58},"1":{"x":148,"y":28},"2":{"x":36,"y":28},"3":{"x":156,"y":10},"4":{"x":55,"y":43}}},"8":{"is_add_obstacles":false,"pos":{"0":{"x":59,"y":47},"1":{"x":37,"y":39},"2":{"x":99,"y":47},"3":{"x":79,"y":15},"4":{"x":86,"y":60}}},"9":{"is_add_obstacles":true,"pos":{"0":{"x":153,"y":37},"1":{"x":39,"y":4},"2":{"x":155,"y":39},"3":{"x":39,"y":40},"4":{"x":4,"y":18}}}}