{"0":{"is_add_obstacles":false},"1":{"is_add_obstacles":false,"pos":{"0":{"x":91,"y":62},"1":{"x":64,"y":56},"2":{"x":84,"y":48},"3":{"x":82,"y":60},"4":{"x":76,"y":29}}},"2":{"is_add_obstacles":false,"pos":{"0":{"x":64,"y":15},"1":{"x":40,"y":41},"2":{"x":40,"y":14},"3":{"x":27,"y":53},"4":{"x":94,"y":11}}},"3":{"is_add_obstacles":false,"pos":{"0":{"x":65,"y":14},"1":{"x":152,"y":62},"2":{"x":54,"y":54},"3":{"x":122,"y":45},"4":{"x":103,"y":57}}},"4":{"is_add_obstacles":false,"pos":{"0":{"x":87,"y":3},"1":{"x":74,"y":56},"2":{"x":57,"y":62},"3":{"x":56,"y":18},"4":{"x":34,"y":6}}},"5":{"is_add_obstacles":false,"pos":{"0":{"x":38,"y":48},"1":{"x":56,"y":17},"2":{"x":41,"y":47},"3":{"x":131,"y":8},"4":{"x":41,"y":53}}},"6":{"is_add_obstacles":false,"pos":{"0":{"x":112,"y":17},"1":{"x":74,"y":47},"2":{"x":52,"y":27},"3":{"x":46,"y":8},"4":{"x":83,"y":41}}},"7":{"is_add_obstacles":false,"pos":{"0":{"x":93,"y":56},"1":{"x":96,"y":51},"2":{"x":127,"y":44},"3":{"x":66,"y":20},"4":{"x":107,"y":18}}},"8":{"is_add_obstacles":false,"pos":{"0":{"x":92,"y":57},"1":{"x":44,"y":29},"2":{"x":108,"y":62},"3":{"x":99,"y":30},"4":{"x":65,"y":29}}},"9":{"is_add_obstacles":false,"pos":{"0":{"x":104,"y":62},"1":{"x":71,"y":2},"2":{"x":54,"y":33},"3":{"x":49,"y":54},"4":{"x":97,"y":11}}}}