{"0":{"is_add_obstacles":false},"1":{"is_add_obstacles":false,"pos":{"0":{"x":13,"y":16},"1":{"x":2,"y":8},"2":{"x":21,"y":20},"3":{"x":15,"y":16},"4":{"x":24,"y":16}}},"2":{"is_add_obstacles":false,"pos":{"0":{"x":12,"y":9},"1":{"x":4,"y":20},"2":{"x":28,"y":11},"3":{"x":8,"y":29},"4":{"x":12,"y":20}}},"3":{"is_add_obstacles":false,"pos":{"0":{"x":28,"y":24},"1":{"x":3,"y":20},"2":{"x":5,"y":28},"3":{"x":19,"y":12},"4":{"x":7,"y":16}}},"4":{"is_add_obstacles":false,"pos":{"0":{"x":8,"y":22},"1":{"x":20,"y":24},"2":{"x":25,"y":28},"3":{"x":28,"y":13},"4":{"x":8,"y":27}}},"5":{"is_add_obstacles":false,"pos":{"0":{"x":16,"y":12},"1":{"x":0,"y":2},"2":{"x":20,"y":9},"3":{"x":10,"y":8},"4":{"x":29,"y":8}}},"6":{"is_add_obstacles":false,"pos":{"0":{"x":24,"y":20},"1":{"x":0,"y":14},"2":{"x":28,"y":7},"3":{"x":12,"y":0},"4":{"x":0,"y":24}}},"7":{"is_add_obstacles":false,"pos":{"0":{"x":13,"y":4},"1":{"x":16,"y":1},"2":{"x":11,"y":20},"3":{"x":28,"y":9},"4":{"x":15,"y":12}}},"8":{"is_add_obstacles":false,"pos":{"0":{"x":29,"y":4},"1":{"x":10,"y":16},"2":{"x":14,"y":12},"3":{"x":21,"y":28},"4":{"x":20,"y":19}}},"9":{"is_add_obstacles":false,"pos":{"0":{"x":22,"y":24},"1":{"x":24,"y":12},"2":{"x":20,"y":10},"3":{"x":24,"y":0},"4":{"x":0,"y":7}}}}