{"0":{"is_add_obstacles":false},"1":{"is_add_obstacles":true,"pos":{"0":{"x":183,"y":22},"1":{"x":243,"y":22},"2":{"x":157,"y":167},"3":{"x":77,"y":162},"4":{"x":227,"y":97}}},"2":{"is_add_obstacles":false,"pos":{"0":{"x":146,"y":240},"1":{"x":99,"y":245},"2":{"x":189,"y":123},"3":{"x":118,"y":191},"4":{"x":2,"y":51}}},"3":{"is_add_obstacles":true,"pos":{"0":{"x":204,"y":57},"1":{"x":225,"y":100},"2":{"x":226,"y":69},"3":{"x":61,"y":143},"4":{"x":152,"y":228}}},"4":{"is_add_obstacles":false,"pos":{"0":{"x":0,"y":194},"1":{"x":9,"y":93},"2":{"x":139,"y":48},"3":{"x":63,"y":214},"4":{"x":47,"y":208}}},"5":{"is_add_obstacles":true,"pos":{"0":{"x":127,"y":45},"1":{"x":52,"y":43},"2":{"x":235,"y":127},"3":{"x":13,"y":178},"4":{"x":177,"y":41}}},"6":{"is_add_obstacles":false,"pos":{"0":{"x":139,"y":49},"1":{"x":156,"y":205},"2":{"x":242,"y":224},"3":{"x":23,"y":215},"4":{"x":56,"y":14}}},"7":{"is_add_obstacles":true,"pos":{"0":{"x":229,"y":63},"1":{"x":188,"y":56},"2":{"x":86,"y":102},"3":{"x":173,"y":95},"4":{"x":108,"y":157}}},"8":{"is_add_obstacles":false,"pos":{"0":{"x":76,"y":113},"1":{"x":13,"y":106},"2":{"x":121,"y":236},"3":{"x":12,"y":121},"4":{"x":161,"y":243}}},"9":{"is_add_obstacles":true,"pos":{"0":{"x":198,"y":54},"1":{"x":124,"y":49},"2":{"x":115,"y":50},"3":{"x":75,"y":42},"4":{"x":75,"y":137}}}}