{"0":{"is_add_obstacles":false},"1":{"is_add_obstacles":true,"pos":{"0":{"x":0,"y":20},"1":{"x":27,"y":12},"2":{"x":19,"y":12},"3":{"x":26,"y":14},"4":{"x":39,"y":2}}},"2":{"is_add_obstacles":true,"pos":{"0":{"x":63,"y":38},"1":{"x":3,"y":7},"2":{"x":62,"y":47},"3":{"x":2,"y":51},"4":{"x":28,"y":27}}},"3":{"is_add_obstacles":true,"pos":{"0":{"x":63,"y":22},"1":{"x":57,"y":52},"2":{"x":50,"y":26},"3":{"x":20,"y":34},"4":{"x":3,"y":26}}},"4":{"is_add_obstacles":true,"pos":{"0":{"x":39,"y":51},"1":{"x":11,"y":60},"2":{"x":5,"y":59},"3":{"x":29,"y":14},"4":{"x":7,"y":44}}},"5":{"is_add_obstacles":true,"pos":{"0":{"x":10,"y":53},"1":{"x":62,"y":10},"2":{"x":46,"y":7},"3":{"x":5,"y":10},"4":{"x":37,"y":15}}},"6":{"is_add_obstacles":true,"pos":{"0":{"x":35,"y":20},"1":{"x":54,"y":20},"2":{"x":43,"y":54},"3":{"x":22,"y":15},"4":{"x":7,"y":4}}},"7":{"is_add_obstacles":true,"pos":{"0":{"x":5,"y":15},"1":{"x":1,"y":60},"2":{"x":51,"y":2},"3":{"x":50,"y":62},"4":{"x":11,"y":6}}},"8":{"is_add_obstacles":true,"pos":{"0":{"x":51,"y":37},"1":{"x":25,"y":44},"2":{"x":35,"y":3},"3":{"x":8,"y":12},"4":{"x":51,"y":29}}},"9":{"is_add_obstacles":true,"pos":{"0":{"x":59,"y":23},"1":{"x":43,"y":41},"2":{"x":17,"y":33},"3":{"x":26,"y":36},"4":{"x":33,"y":34}}}}