{"0":{"is_add_obstacles":false},"1":{"is_add_obstacles":false,"pos":{"0":{"x":129,"y":20},"1":{"x":78,"y":2},"2":{"x":107,"y":47},"3":{"x":128,"y":33},"4":{"x":119,"y":8}}},"2":{"is_add_obstacles":false,"pos":{"0":{"x":123,"y":47},"1":{"x":116,"y":0},"2":{"x":32,"y":45},"3":{"x":54,"y":26},"4":{"x":123,"y":36}}},"3":{"is_add_obstacles":false,"pos":{"0":{"x":57,"y":12},"1":{"x":87,"y":44},"2":{"x":82,"y":0},"3":{"x":15,"y":62},"4":{"x":123,"y":51}}},"4":{"is_add_obstacles":false,"pos":{"0":{"x":130,"y":62},"1":{"x":66,"y":8},"2":{"x":119,"y":62},"3":{"x":61,"y":21},"4":{"x":65,"y":32}}},"5":{"is_add_obstacles":false,"pos":{"0":{"x":71,"y":3},"1":{"x":56,"y":42},"2":{"x":120,"y":29},"3":{"x":46,"y":27},"4":{"x":39,"y":50}}},"6":{"is_add_obstacles":false,"pos":{"0":{"x":93,"y":56},"1":{"x":121,"y":27},"2":{"x":118,"y":20},"3":{"x":83,"y":29},"4":{"x":44,"y":33}}},"7":{"is_add_obstacles":false,"pos":{"0":{"x":55,"y":5},"1":{"x":29,"y":9},"2":{"x":60,"y":44},"3":{"x":60,"y":24},"4":{"x":35,"y":53}}},"8":{"is_add_obstacles":false,"pos":{"0":{"x":160,"y":5},"1":{"x":61,"y":35},"2":{"x":132,"y":11},"3":{"x":51,"y":18},"4":{"x":0,"y":10}}},"9":{"is_add_obstacles":false,"pos":{"0":{"x":38,"y":41},"1":{"x":87,"y":45},"2":{"x":48,"y":35},"3":{"x":123,"y":15},"4":{"x":40,"y":53}}}}