{"0":{"is_add_obstacles":false},"1":{"is_add_obstacles":true,"pos":{"0":{"x":157,"y":168},"1":{"x":245,"y":76},"2":{"x":161,"y":137},"3":{"x":171,"y":70},"4":{"x":90,"y":97}}},"2":{"is_add_obstacles":false,"pos":{"0":{"x":5,"y":33},"1":{"x":123,"y":176},"2":{"x":223,"y":19},"3":{"x":170,"y":16},"4":{"x":4,"y":92}}},"3":{"is_add_obstacles":true,"pos":{"0":{"x":214,"y":41},"1":{"x":129,"y":44},"2":{"x":69,"y":228},"3":{"x":162,"y":134},"4":{"x":186,"y":50}}},"4":{"is_add_obstacles":false,"pos":{"0":{"x":107,"y":29},"1":{"x":192,"y":99},"2":{"x":239,"y":162},"3":{"x":139,"y":237},"4":{"x":88,"y":236}}},"5":{"is_add_obstacles":true,"pos":{"0":{"x":10,"y":190},"1":{"x":52,"y":163},"2":{"x":126,"y":97},"3":{"x":238,"y":62},"4":{"x":190,"y":41}}},"6":{"is_add_obstacles":false,"pos":{"0":{"x":170,"y":220},"1":{"x":32,"y":254},"2":{"x":65,"y":114},"3":{"x":12,"y":45},"4":{"x":24,"y":61}}},"7":{"is_add_obstacles":true,"pos":{"0":{"x":90,"y":149},"1":{"x":216,"y":136},"2":{"x":213,"y":179},"3":{"x":141,"y":90},"4":{"x":208,"y":88}}},"8":{"is_add_obstacles":false,"pos":{"0":{"x":15,"y":24},"1":{"x":92,"y":30},"2":{"x":241,"y":134},"3":{"x":60,"y":239},"4":{"x":202,"y":45}}},"9":{"is_add_obstacles":true,"pos":{"0":{"x":250,"y":140},"1":{"x":222,"y":215},"2":{"x":137,"y":93},"3":{"x":220,"y":216},"4":{"x":175,"y":60}}}}