{"0":{"is_add_obstacles":false},"1":{"is_add_obstacles":true,"pos":{"0":{"x":106,"y":51},"1":{"x":26,"y":169},"2":{"x":216,"y":34},"3":{"x":239,"y":7},"4":{"x":229,"y":182}}},"2":{"is_add_obstacles":true,"pos":{"0":{"x":26,"y":162},"1":{"x":148,"y":50},"2":{"x":205,"y":91},"3":{"x":97,"y":139},"4":{"x":89,"y":40}}},"3":{"is_add_obstacles":true,"pos":{"0":{"x":36,"y":172},"1":{"x":215,"y":209},"2":{"x":229,"y":191},"3":{"x":36,"y":160},"4":{"x":98,"y":49}}},"4":{"is_add_obstacles":true,"pos":{"0":{"x":195,"y":36},"1":{"x":98,"y":212},"2":{"x":150,"y":93},"3":{"x":13,"y":152},"4":{"x":175,"y":185}}},"5":{"is_add_obstacles":true,"pos":{"0":{"x":88,"y":56},"1":{"x":93,"y":85},"2":{"x":59,"y":80},"3":{"x":167,"y":168},"4":{"x":199,"y":201}}},"6":{"is_add_obstacles":true,"pos":{"0":{"x":84,"y":223},"1":{"x":58,"y":81},"2":{"x":106,"y":223},"3":{"x":82,"y":100},"4":{"x":181,"y":27}}},"7":{"is_add_obstacles":true,"pos":{"0":{"x":208,"y":45},"1":{"x":202,"y":192},"2":{"x":56,"y":156},"3":{"x":123,"y":161},"4":{"x":82,"y":185}}},"8":{"is_add_obstacles":true,"pos":{"0":{"x":230,"y":105},"1":{"x":236,"y":80},"2":{"x":80,"y":149},"3":{"x":126,"y":163},"4":{"x":66,"y":34}}},"9":{"is_add_obstacles":true,"pos":{"0":{"x":158,"y":53},"1":{"x":78,"y":59},"2":{"x":42,"y":65},"3":{"x":227,"y":204},"4":{"x":102,"y":231}}}}