{"0":{"is_add_obstacles":false},"1":{"is_add_obstacles":true,"pos":{"0":{"x":164,"y":148},"1":{"x":158,"y":131},"2":{"x":184,"y":19},"3":{"x":173,"y":38},"4":{"x":230,"y":77}}},"2":{"is_add_obstacles":true,"pos":{"0":{"x":235,"y":75},"1":{"x":226,"y":123},"2":{"x":104,"y":105},"3":{"x":198,"y":80},"4":{"x":84,"y":213}}},"3":{"is_add_obstacles":true,"pos":{"0":{"x":172,"y":125},"1":{"x":226,"y":85},"2":{"x":90,"y":40},"3":{"x":16,"y":73},"4":{"x":10,"y":192}}},"4":{"is_add_obstacles":true,"pos":{"0":{"x":63,"y":142},"1":{"x":235,"y":200},"2":{"x":191,"y":40},"3":{"x":211,"y":190},"4":{"x":231,"y":107}}},"5":{"is_add_obstacles":true,"pos":{"0":{"x":225,"y":85},"1":{"x":164,"y":130},"2":{"x":175,"y":99},"3":{"x":81,"y":104},"4":{"x":73,"y":41}}},"6":{"is_add_obstacles":true,"pos":{"0":{"x":175,"y":94},"1":{"x":71,"y":82},"2":{"x":165,"y":26},"3":{"x":241,"y":110},"4":{"x":74,"y":40}}},"7":{"is_add_obstacles":true,"pos":{"0":{"x":56,"y":89},"1":{"x":251,"y":129},"2":{"x":218,"y":36},"3":{"x":55,"y":72},"4":{"x":104,"y":112}}},"8":{"is_add_obstacles":true,"pos":{"0":{"x":182,"y":36},"1":{"x":205,"y":81},"2":{"x":246,"y":45},"3":{"x":235,"y":13},"4":{"x":147,"y":209}}},"9":{"is_add_obstacles":true,"pos":{"0":{"x":251,"y":143},"1":{"x":163,"y":115},"2":{"x":71,"y":41},"3":{"x":127,"y":51},"4":{"x":97,"y":174}}}}