{"0":{"is_add_obstacles":false},"1":{"is_add_obstacles":true,"pos":{"0":{"x":199,"y":65},"1":{"x":226,"y":192},"2":{"x":149,"y":229},"3":{"x":217,"y":185},"4":{"x":208,"y":69}}},"2":{"is_add_obstacles":true,"pos":{"0":{"x":81,"y":182},"1":{"x":139,"y":206},"2":{"x":235,"y":28},"3":{"x":11,"y":164},"4":{"x":136,"y":51}}},"3":{"is_add_obstacles":true,"pos":{"0":{"x":52,"y":41},"1":{"x":249,"y":133},"2":{"x":130,"y":108},"3":{"x":119,"y":157},"4":{"x":214,"y":70}}},"4":{"is_add_obstacles":true,"pos":{"0":{"x":132,"y":159},"1":{"x":140,"y":44},"2":{"x":222,"y":189},"3":{"x":106,"y":80},"4":{"x":132,"y":48}}},"5":{"is_add_obstacles":true,"pos":{"0":{"x":169,"y":123},"1":{"x":169,"y":135},"2":{"x":125,"y":213},"3":{"x":144,"y":26},"4":{"x":53,"y":155}}},"6":{"is_add_obstacles":true,"pos":{"0":{"x":75,"y":147},"1":{"x":72,"y":232},"2":{"x":245,"y":18},"3":{"x":228,"y":213},"4":{"x":16,"y":163}}},"7":{"is_add_obstacles":true,"pos":{"0":{"x":181,"y":19},"1":{"x":85,"y":152},"2":{"x":224,"y":99},"3":{"x":245,"y":33},"4":{"x":160,"y":143}}},"8":{"is_add_obstacles":true,"pos":{"0":{"x":49,"y":133},"1":{"x":50,"y":65},"2":{"x":91,"y":224},"3":{"x":111,"y":46},"4":{"x":236,"y":9}}},"9":{"is_add_obstacles":true,"pos":{"0":{"x":111,"y":159},"1":{"x":206,"y":177},"2":{"x":133,"y":217},"3":{"x":60,"y":175},"4":{"x":76,"y":58}}}}