{"0":{"is_add_obstacles":false},"1":{"is_add_obstacles":true,"pos":{"0":{"x":98,"y":207},"1":{"x":233,"y":10},"2":{"x":128,"y":65},"3":{"x":98,"y":144},"4":{"x":213,"y":64}}},"2":{"is_add_obstacles":false,"pos":{"0":{"x":213,"y":149},"1":{"x":203,"y":22},"2":{"x":220,"y":171},"3":{"x":194,"y":103},"4":{"x":179,"y":194}}},"3":{"is_add_obstacles":true,"pos":{"0":{"x":202,"y":178},"1":{"x":133,"y":163},"2":{"x":146,"y":166},"3":{"x":169,"y":26},"4":{"x":79,"y":91}}},"4":{"is_add_obstacles":false,"pos":{"0":{"x":37,"y":138},"1":{"x":48,"y":121},"2":{"x":131,"y":189},"3":{"x":237,"y":235},"4":{"x":122,"y":72}}},"5":{"is_add_obstacles":true,"pos":{"0":{"x":87,"y":93},"1":{"x":205,"y":70},"2":{"x":135,"y":210},"3":{"x":211,"y":54},"4":{"x":53,"y":146}}},"6":{"is_add_obstacles":false,"pos":{"0":{"x":115,"y":147},"1":{"x":191,"y":210},"2":{"x":180,"y":106},"3":{"x":104,"y":66},"4":{"x":50,"y":200}}},"7":{"is_add_obstacles":true,"pos":{"0":{"x":130,"y":217},"1":{"x":48,"y":175},"2":{"x":250,"y":144},"3":{"x":168,"y":19},"4":{"x":24,"y":174}}},"8":{"is_add_obstacles":false,"pos":{"0":{"x":248,"y":109},"1":{"x":181,"y":256},"2":{"x":192,"y":108},"3":{"x":21,"y":256},"4":{"x":27,"y":2}}},"9":{"is_add_obstacles":true,"pos":{"0":{"x":213,"y":92},"1":{"x":99,"y":203},"2":{"x":157,"y":28},"3":{"x":242,"y":29},"4":{"x":137,"y":154}}}}