{"0":{"is_add_obstacles":false},"1":{"is_add_obstacles":true,"pos":{"0":{"x":12,"y":23},"1":{"x":26,"y":22},"2":{"x":14,"y":16},"3":{"x":6,"y":12},"4":{"x":6,"y":27}}},"2":{"is_add_obstacles":true,"pos":{"0":{"x":18,"y":21},"1":{"x":16,"y":25},"2":{"x":30,"y":9},"3":{"x":30,"y":7},"4":{"x":12,"y":16}}},"3":{"is_add_obstacles":true,"pos":{"0":{"x":3,"y":10},"1":{"x":0,"y":19},"2":{"x":9,"y":23},"3":{"x":3,"y":27},"4":{"x":8,"y":5}}},"4":{"is_add_obstacles":true,"pos":{"0":{"x":23,"y":18},"1":{"x":24,"y":1},"2":{"x":12,"y":19},"3":{"x":26,"y":31},"4":{"x":25,"y":13}}},"5":{"is_add_obstacles":true,"pos":{"0":{"x":16,"y":16},"1":{"x":15,"y":28},"2":{"x":30,"y":27},"3":{"x":28,"y":25},"4":{"x":31,"y":28}}},"6":{"is_add_obstacles":true,"pos":{"0":{"x":10,"y":23},"1":{"x":0,"y":11},"2":{"x":19,"y":11},"3":{"x":13,"y":15},"4":{"x":29,"y":22}}},"7":{"is_add_obstacles":true},"8":{"is_add_obstacles":true},"9":{"is_add_obstacles":true}}