{"0":{"is_add_obstacles":false},"1":{"is_add_obstacles":true,"pos":{"0":{"x":14,"y":26},"1":{"x":148,"y":41},"2":{"x":39,"y":49},"3":{"x":50,"y":4},"4":{"x":142,"y":59}}},"2":{"is_add_obstacles":true,"pos":{"0":{"x":102,"y":55},"1":{"x":6,"y":48},"2":{"x":47,"y":14},"3":{"x":83,"y":46},"4":{"x":13,"y":55}}},"3":{"is_add_obstacles":true,"pos":{"0":{"x":106,"y":52},"1":{"x":59,"y":49},"2":{"x":95,"y":49},"3":{"x":151,"y":32},"4":{"x":91,"y":40}}},"4":{"is_add_obstacles":true,"pos":{"0":{"x":66,"y":49},"1":{"x":20,"y":29},"2":{"x":16,"y":49},"3":{"x":125,"y":25},"4":{"x":133,"y":25}}},"5":{"is_add_obstacles":true,"pos":{"0":{"x":3,"y":13},"1":{"x":141,"y":8},"2":{"x":10,"y":57},"3":{"x":55,"y":4},"4":{"x":8,"y":31}}},"6":{"is_add_obstacles":true,"pos":{"0":{"x":144,"y":47},"1":{"x":152,"y":42},"2":{"x":138,"y":23},"3":{"x":20,"y":47},"4":{"x":2,"y":54}}},"7":{"is_add_obstacles":true,"pos":{"0":{"x":155,"y":8},"1":{"x":49,"y":25},"2":{"x":51,"y":19},"3":{"x":25,"y":58},"4":{"x":75,"y":31}}},"8":{"is_add_obstacles":true,"pos":{"0":{"x":155,"y":48},"1":{"x":145,"y":50},"2":{"x":24,"y":42},"3":{"x":5,"y":12},"4":{"x":62,"y":4}}},"9":{"is_add_obstacles":true,"pos":{"0":{"x":93,"y":16},"1":{"x":101,"y":28},"2":{"x":82,"y":31},"3":{"x":7,"y":12},"4":{"x":124,"y":49}}}}