{"0":{"is_add_obstacles":false},"1":{"is_add_obstacles":false,"pos":{"0":{"x":89,"y":32},"1":{"x":129,"y":30},"2":{"x":26,"y":24},"3":{"x":122,"y":21},"4":{"x":42,"y":54}}},"2":{"is_add_obstacles":false,"pos":{"0":{"x":26,"y":30},"1":{"x":111,"y":41},"2":{"x":78,"y":8},"3":{"x":129,"y":57},"4":{"x":39,"y":20}}},"3":{"is_add_obstacles":false,"pos":{"0":{"x":126,"y":15},"1":{"x":109,"y":41},"2":{"x":33,"y":50},"3":{"x":92,"y":21},"4":{"x":160,"y":39}}},"4":{"is_add_obstacles":false,"pos":{"0":{"x":86,"y":41},"1":{"x":111,"y":2},"2":{"x":76,"y":9},"3":{"x":138,"y":62},"4":{"x":112,"y":5}}},"5":{"is_add_obstacles":false,"pos":{"0":{"x":74,"y":50},"1":{"x":57,"y":36},"2":{"x":79,"y":5},"3":{"x":114,"y":15},"4":{"x":122,"y":53}}},"6":{"is_add_obstacles":false,"pos":{"0":{"x":38,"y":35},"1":{"x":60,"y":41},"2":{"x":112,"y":54},"3":{"x":101,"y":21},"4":{"x":160,"y":20}}},"7":{"is_add_obstacles":false,"pos":{"0":{"x":104,"y":41},"1":{"x":71,"y":6},"2":{"x":33,"y":0},"3":{"x":43,"y":50},"4":{"x":52,"y":6}}},"8":{"is_add_obstacles":false,"pos":{"0":{"x":93,"y":2},"1":{"x":71,"y":20},"2":{"x":86,"y":53},"3":{"x":65,"y":47},"4":{"x":94,"y":54}}},"9":{"is_add_obstacles":false,"pos":{"0":{"x":117,"y":57},"1":{"x":38,"y":39},"2":{"x":10,"y":62},"3":{"x":131,"y":32},"4":{"x":121,"y":48}}}}