{"0":{"is_add_obstacles":false},"1":{"is_add_obstacles":true,"pos":{"0":{"x":91,"y":52},"1":{"x":95,"y":7},"2":{"x":69,"y":27},"3":{"x":158,"y":25},"4":{"x":128,"y":46}}},"2":{"is_add_obstacles":true,"pos":{"0":{"x":66,"y":19},"1":{"x":154,"y":34},"2":{"x":141,"y":39},"3":{"x":69,"y":3},"4":{"x":111,"y":19}}},"3":{"is_add_obstacles":true,"pos":{"0":{"x":41,"y":40},"1":{"x":10,"y":14},"2":{"x":12,"y":12},"3":{"x":116,"y":4},"4":{"x":8,"y":36}}},"4":{"is_add_obstacles":true,"pos":{"0":{"x":146,"y":61},"1":{"x":152,"y":55},"2":{"x":54,"y":7},"3":{"x":108,"y":52},"4":{"x":84,"y":7}}},"5":{"is_add_obstacles":true,"pos":{"0":{"x":68,"y":43},"1":{"x":112,"y":22},"2":{"x":126,"y":10},"3":{"x":25,"y":3},"4":{"x":79,"y":7}}},"6":{"is_add_obstacles":true,"pos":{"0":{"x":30,"y":58},"1":{"x":113,"y":4},"2":{"x":147,"y":47},"3":{"x":6,"y":61},"4":{"x":1,"y":3}}},"7":{"is_add_obstacles":true,"pos":{"0":{"x":117,"y":61},"1":{"x":146,"y":20},"2":{"x":125,"y":52},"3":{"x":155,"y":60},"4":{"x":21,"y":17}}},"8":{"is_add_obstacles":true,"pos":{"0":{"x":3,"y":4},"1":{"x":148,"y":43},"2":{"x":58,"y":50},"3":{"x":6,"y":35},"4":{"x":14,"y":60}}},"9":{"is_add_obstacles":true,"pos":{"0":{"x":107,"y":58},"1":{"x":139,"y":30},"2":{"x":2,"y":51},"3":{"x":55,"y":40},"4":{"x":113,"y":25}}}}