{"0":{"is_add_obstacles":false},"1":{"is_add_obstacles":true,"pos":{"0":{"x":171,"y":114},"1":{"x":218,"y":187},"2":{"x":101,"y":165},"3":{"x":51,"y":46},"4":{"x":73,"y":211}}},"2":{"is_add_obstacles":false,"pos":{"0":{"x":72,"y":233},"1":{"x":37,"y":214},"2":{"x":192,"y":24},"3":{"x":251,"y":81},"4":{"x":235,"y":245}}},"3":{"is_add_obstacles":true,"pos":{"0":{"x":133,"y":147},"1":{"x":103,"y":158},"2":{"x":51,"y":80},"3":{"x":175,"y":92},"4":{"x":175,"y":168}}},"4":{"is_add_obstacles":false,"pos":{"0":{"x":162,"y":188},"1":{"x":11,"y":25},"2":{"x":135,"y":202},"3":{"x":32,"y":132},"4":{"x":57,"y":252}}},"5":{"is_add_obstacles":true,"pos":{"0":{"x":211,"y":78},"1":{"x":239,"y":88},"2":{"x":229,"y":96},"3":{"x":130,"y":157},"4":{"x":233,"y":196}}},"6":{"is_add_obstacles":false,"pos":{"0":{"x":223,"y":16},"1":{"x":167,"y":4},"2":{"x":43,"y":237},"3":{"x":32,"y":255},"4":{"x":155,"y":60}}},"7":{"is_add_obstacles":true,"pos":{"0":{"x":242,"y":101},"1":{"x":224,"y":116},"2":{"x":99,"y":43},"3":{"x":123,"y":38},"4":{"x":183,"y":149}}},"8":{"is_add_obstacles":false,"pos":{"0":{"x":57,"y":213},"1":{"x":66,"y":15},"2":{"x":59,"y":18},"3":{"x":237,"y":157},"4":{"x":86,"y":249}}},"9":{"is_add_obstacles":true,"pos":{"0":{"x":45,"y":173},"1":{"x":129,"y":25},"2":{"x":47,"y":76},"3":{"x":188,"y":57},"4":{"x":163,"y":17}}}}