{"0":{"is_add_obstacles":false},"1":{"is_add_obstacles":true,"pos":{"0":{"x":124,"y":117},"1":{"x":128,"y":86},"2":{"x":45,"y":142},"3":{"x":104,"y":150},"4":{"x":136,"y":35}}},"2":{"is_add_obstacles":false,"pos":{"0":{"x":204,"y":115},"1":{"x":14,"y":30},"2":{"x":202,"y":96},"3":{"x":196,"y":113},"4":{"x":44,"y":96}}},"3":{"is_add_obstacles":true,"pos":{"0":{"x":152,"y":119},"1":{"x":9,"y":202},"2":{"x":168,"y":166},"3":{"x":13,"y":154},"4":{"x":70,"y":230}}},"4":{"is_add_obstacles":false,"pos":{"0":{"x":55,"y":96},"1":{"x":38,"y":122},"2":{"x":34,"y":62},"3":{"x":172,"y":211},"4":{"x":148,"y":14}}},"5":{"is_add_obstacles":true,"pos":{"0":{"x":241,"y":39},"1":{"x":123,"y":33},"2":{"x":78,"y":101},"3":{"x":239,"y":78},"4":{"x":172,"y":63}}},"6":{"is_add_obstacles":false,"pos":{"0":{"x":156,"y":39},"1":{"x":227,"y":255},"2":{"x":114,"y":7},"3":{"x":165,"y":218},"4":{"x":51,"y":128}}},"7":{"is_add_obstacles":true,"pos":{"0":{"x":103,"y":111},"1":{"x":215,"y":81},"2":{"x":190,"y":166},"3":{"x":130,"y":108},"4":{"x":183,"y":124}}},"8":{"is_add_obstacles":false,"pos":{"0":{"x":109,"y":2},"1":{"x":149,"y":194},"2":{"x":162,"y":223},"3":{"x":41,"y":233},"4":{"x":49,"y":248}}},"9":{"is_add_obstacles":true,"pos":{"0":{"x":248,"y":138},"1":{"x":113,"y":154},"2":{"x":167,"y":99},"3":{"x":137,"y":11},"4":{"x":129,"y":61}}}}